friendly_matrix/__init__.py
friendly_matrix/compute_matrix.py
friendly_matrix/constants.py
friendly_matrix/formatting.py
friendly_matrix/friendly_matrix.py
friendly_matrix/methods.py
friendly_matrix/operations.py
numpy_string_indexed-0.0.3.dist-info/LICENSE
numpy_string_indexed-0.0.3.dist-info/METADATA
numpy_string_indexed-0.0.3.dist-info/WHEEL
numpy_string_indexed-0.0.3.dist-info/top_level.txt
numpy_string_indexed-0.0.3.dist-info/RECORD
