Metadata-Version: 2.1
Name: numpy-string-indexed
Version: 0.0.3
Summary: A NumPy extension that allows arrays to be indexed using labels
Home-page: https://github.com/AitanG/numpy-string-indexed
Author: Aitan Grossman
Author-email: aitan.gros@gmail.com
License: UNKNOWN
Project-URL: Bug Tracker, https://github.com/AitanG/numpy-string-indexed/issues
Platform: UNKNOWN
Classifier: Programming Language :: Python :: 3
Classifier: License :: OSI Approved :: MIT License
Classifier: Operating System :: OS Independent
Classifier: Development Status :: 4 - Beta
Classifier: Intended Audience :: Developers
Classifier: Topic :: Software Development :: Libraries :: Python Modules
Requires-Python: >=3.6
License-File: LICENSE
